{
  "name": "The Diplomat",
  "permalink": "the-diplomat",
  "description": "Not every mission has to end with gunfire or a high speed getaway. You use your charm and your tact to defuse tense situations, win people over, and maintain relationships with your allies. You're a great negotiator, and you know how to get what you need through conversation.",
  "shorthand": "Diplomat",
  "moves": [
    {
      "name": "Calming touch",
      "description": "You can diffuse tense interactions more easily than most (+1 act under pressure)"
    },
    {
      "name": "Gesture of goodwill",
      "description": "If you give something of value to someone, they are more likely to help you (a 7-9 is treated like 10+ manipulate someone)"
    },
    {
      "name": "Carry a big stick",
      "description": "If negotiations break down, you're prepared to defend yourself (+1 kick some ass, protect someone)"
    },
    {
      "name": "Home field advantage",
      "description": "If you are on your home planet, you have the upper hand in negotiations (+1 manipulate someone)"
    },
    {
      "name": "Gentle approach",
      "description": "Use empathy and compassion rather than intimidation to get information from people (+1 investigate, read a bad situation)"
    },
    {
      "name": "Cooler heads",
      "description": "Keeping calm has an effect on your allies (+1 help out)"
    },
    {
      "name": "Tough negotiator",
      "description": "Talk your way out of life or death situations (+1 act under pressure)"
    }
  ],
  "weapons": [
    {
      "name": "Hidden dagger",
      "tags": [
        "1 harm",
        "intimate",
        "quick",
        "small"
      ]
    },
    {
      "name": "Stun gun",
      "tags": [
        "1 harm",
        "close",
        "stun"
      ]
    },
    {
      "name": "Cane",
      "tags": [
        "1 harm",
        "close",
        "balanced",
        "useful"
      ]
    },
    {
      "name": "Poison drops",
      "tags": [
        "3 harm",
        "intimate",
        "innocuous",
        "many"
      ]
    }
  ],
  "items": [
    {
      "name": "Flak jacket",
      "tags": [
        "2 armor",
        "heavy"
      ]
    },
    {
      "name": "Protective vest",
      "tags": [
        "1 armor",
        "light"
      ]
    },
    {
      "name": "Listening device",
      "tags": [
        "listen to conversations at a distance"
      ]
    },
    {
      "name": "Box of goodies",
      "tags": [
        "candies and treats from home that you can use to ingratiate yourself to the locals"
      ]
    }
  ],
  "histories": [
    "This explorer used to work with you before",
    "You had to put out some fires because of this explorer's actions in the past",
    "This explorer saved your life",
    "You made a deal with this explorer's sworn enemy",
    "This explorer gets frustrated with negotiations and wants to blow things up all the time",
    "You negotiated peace, keeping this explorer out of harm's way",
    "This explorer considers you a mentor and looks up to you ",
    "This explorer thinks you're unqualified for your job",
    "This explorer has a terrible poker face and needs to be kept away from negotiations"
  ],
  "improvements": [
    "Get +1 Charm (max +3)",
    "Get +1 Cool (max +2)",
    "Get +1 Sharp (max +2)",
    "Get +1 Tough (max +2)",
    "Take another Diplomat move",
    "Take another Diplomat move",
    "Gain an ally",
    "Take a move from another archetype",
    "Take a move from another archetype"
  ],
  "advancedImprovements": [
    "Get +1 to any rating (max +3)",
    "Get back one used Luck point",
    "Change this explorer to a new type",
    "Create a second explorer to play in addition to this one",
    "Mark two of the basic moves as advanced",
    "Mark another two of the basic moves as advanced",
    "Retire this explorer"
  ]
}
